kymo_stream/__init__.py
kymo_stream/main.py
kymo_stream-0.1.2.dist-info/WHEEL
kymo_stream-0.1.2.dist-info/entry_points.txt
kymo_stream-0.1.2.dist-info/METADATA
kymo_stream-0.1.2.dist-info/RECORD
