Metadata-Version: 2.3
Name: kymo-stream
Version: 0.1.2
Summary: Add your description here
Author: Talmo Pereira
Author-email: Talmo Pereira <talmo@kymo.io>
Requires-Dist: click>=8.2.1
Requires-Dist: numpy>=2.3.2
Requires-Dist: opencv-python>=4.11.0.86
Requires-Dist: ultralytics>=8.3.185
Requires-Python: >=3.12
